client/__init__.py
client/api/__init__.py
client/api/notebook.py
gradememaybe/__init__.py
gradememaybe/notebook.py
gradememaybe/ok.py
gradememaybe/utils.py
gradememaybe-0.6.dist-info/METADATA
gradememaybe-0.6.dist-info/RECORD
gradememaybe-0.6.dist-info/WHEEL
gradememaybe-0.6.dist-info/top_level.txt
okgrade/__init__.py
okgrade/doctest.py
okgrade/grader.py
okgrade/notebook.py
okgrade/result.py
okgrade/utils.py
